{
    "concepts": {
        "actor": {
            "hypernym": "profession"
        }
    },
    "labels": [
        {
            "concept": "actor",
            "label": {
                "singular": "actor",
                "plural": "actors"
            },
            "language": "en"
        },
        {
            "concept": "actor",
            "label": {
                "singular": "näyttelijä",
                "plural": "näyttelijät"
            },
            "language": "fi"
        },
        {
            "concept": "actor",
            "label": {
                "singular": {
                    "feminine": "de actrice",
                    "masculine": "de acteur"
                },
                "plural": {
                    "feminine:": "de actrices",
                    "masculine": "de acteurs"
                }
            },
            "language": "nl"
        }
    ]
}
