{
    "concepts": {
        "audience": {}
    },
    "labels": [
        {
            "concept": "audience",
            "label": {
                "singular": "audience",
                "plural": "audiences"
            },
            "language": "en"
        },
        {
            "concept": "audience",
            "label": {
                "singular": "yleisö",
                "plural": "yleisöt"
            },
            "language": "fi"
        },
        {
            "concept": "audience",
            "label": {
                "singular": "het publiek",
                "plural": "de publieken"
            },
            "language": "nl"
        }
    ]
}
