{
    "concepts": {
        "cup": {},
        "coffee cup": {
            "hypernym": "cup"
        }
    },
    "labels": {
        "en": [
            {
                "concept": "cup",
                "label": "cup"
            },
            {
                "concept": "coffee cup",
                "label": "coffee cup",
                "roots": [
                    "coffee",
                    "cup"
                ]
            }
        ],
        "fi": [
            {
                "concept": "cup",
                "label": "kuppi"
            },
            {
                "concept": "coffee cup",
                "label": "kahvikuppi",
                "roots": [
                    "kahvi",
                    "kuppi"
                ]
            }
        ],
        "nl": [
            {
                "concept": "cup",
                "label": "het kopje"
            },
            {
                "concept": "coffee cup",
                "label": "het koffiekopje",
                "roots": [
                    "de koffie",
                    "het kopje"
                ]
            }
        ]
    }
}
