{
    "concepts": {
        "food": {
            "holonym": "food and drink"
        },
        "mealtime": {},
        "drink": {
            "holonym": "food and drink"
        },
        "food and drink": {},
        "vegetable": {
            "hypernym": "food"
        },
        "meal": {},
        "breakfast": {
            "hypernym": "meal"
        },
        "snack": {
            "hypernym": "food"
        },
        "dinner": {
            "hypernym": "meal"
        },
        "evening snack": {
            "hypernym": "snack"
        },
        "appetiser": {
            "holonym": "meal"
        },
        "main dish": {
            "holonym": "meal"
        },
        "dessert": {
            "holonym": "meal",
            "hypernym": "food"
        },
        "macaroni casserole": {
            "hypernym": "food"
        },
        "rice": {
            "hypernym": "food"
        },
        "pasta": {
            "hypernym": "food"
        },
        "hamburger": {
            "hypernym": "meat"
        },
        "wiener": {
            "hypernym": "meat"
        },
        "shrimp": {
            "hypernym": "food"
        },
        "chicken": {
            "hypernym": "meat"
        },
        "beef": {
            "hypernym": "meat"
        },
        "pork": {
            "hypernym": "meat"
        },
        "dressing": {
            "hypernym": "food"
        },
        "ketchup": {
            "hypernym": "food"
        },
        "bread": {
            "hypernym": "food"
        },
        "karelian pasty": {
            "hypernym": "food"
        },
        "bread roll": {
            "hypernym": "food"
        },
        "butter": {
            "hypernym": "food"
        },
        "meat": {
            "hypernym": "food"
        },
        "milk": {
            "hypernym": "drink"
        },
        "buttermilk": {
            "hypernym": "drink"
        },
        "oat milk": {
            "hypernym": "drink"
        },
        "hot chocolate": {
            "hypernym": "drink"
        },
        "yoghurt": {
            "hypernym": "food"
        },
        "honey": {
            "hypernym": "food"
        },
        "jam": {
            "hypernym": "food"
        },
        "sausage": {
            "hypernym": "meat"
        },
        "ham": {
            "hypernym": "meat"
        },
        "mämmi": {
            "hypernym": "food"
        },
        "pizza": {
            "hypernym": "food"
        },
        "berry": {
            "hypernym": "fruit"
        },
        "strawberry": {
            "hypernym": "berry"
        },
        "cloudberry": {
            "hypernym": "berry"
        },
        "raspberry": {
            "hypernym": "berry"
        },
        "bilberry": {
            "hypernym": "berry"
        },
        "lingonberry": {
            "hypernym": "berry"
        },
        "spice": {
            "hypernym": "food"
        },
        "juice": {
            "hypernym": "drink"
        },
        "apple": {
            "hypernym": "fruit"
        },
        "potato": {
            "hypernym": "food"
        },
        "steak": {
            "hypernym": "meat"
        },
        "pepper": {
            "hypernym": "food"
        },
        "salad": {
            "hypernym": "food"
        },
        "cabbage": {
            "hypernym": "vegetable"
        },
        "mustard": {
            "hypernym": "food"
        },
        "lemon": {
            "hypernym": "fruit"
        },
        "plum": {
            "hypernym": "fruit"
        },
        "peach": {
            "hypernym": "fruit"
        },
        "grape": {
            "hypernym": "fruit"
        },
        "sugar": {
            "hypernym": "food"
        },
        "salt": {
            "hypernym": "food"
        },
        "cucumber": {
            "hypernym": "vegetable"
        },
        "carrot": {
            "hypernym": "vegetable"
        },
        "olive": {
            "hypernym": "vegetable"
        },
        "soy": {
            "hypernym": "food"
        },
        "oil": {
            "hypernym": "food"
        },
        "vinegar": {
            "hypernym": "food"
        },
        "tomato": {
            "hypernym": "vegetable"
        },
        "sandwich": {
            "hypernym": "bread"
        },
        "nut": {
            "hypernym": "food"
        },
        "cherry": {
            "hypernym": "fruit"
        },
        "currant": {
            "hypernym": "berry"
        },
        "cider": {
            "hypernym": "drink"
        },
        "wine": {
            "hypernym": "drink"
        },
        "beer": {
            "hypernym": "drink"
        },
        "soft drink": {
            "hypernym": "drink"
        },
        "tea": {
            "hypernym": "drink"
        },
        "pear": {
            "hypernym": "fruit"
        },
        "cauliflower": {
            "hypernym": "vegetable"
        },
        "egg": {
            "hypernym": "food"
        },
        "aubergine": {
            "hypernym": "vegetable"
        },
        "corn": {
            "hypernym": "vegetable"
        },
        "garlic": {
            "hypernym": "vegetable"
        },
        "paprika": {
            "hypernym": "vegetable"
        },
        "pea": {
            "hypernym": "vegetable"
        },
        "bean": {
            "hypernym": "vegetable"
        },
        "zucchini": {
            "hypernym": "vegetable"
        },
        "cookie": {
            "hypernym": "food"
        },
        "pie": {
            "hypernym": "food"
        },
        "cinnamon roll": {
            "hypernym": "food"
        },
        "cream": {
            "hypernym": "food"
        },
        "whipped cream": {
            "hypernym": "cream"
        },
        "candy": {
            "hypernym": "food"
        },
        "chocolate": {
            "hypernym": "food"
        },
        "chocolate ice cream": {
            "hypernym": "ice cream"
        },
        "vanilla": {
            "hypernym": "food"
        },
        "banana": {
            "hypernym": "fruit"
        },
        "pineapple": {
            "hypernym": "fruit"
        },
        "melon": {
            "hypernym": "fruit"
        },
        "cocktail": {
            "hypernym": "drink"
        },
        "tray": {},
        "fork": {},
        "knife": {},
        "spoon": {},
        "glass": {},
        "mug": {},
        "bowl": {},
        "bottle": {},
        "plate": {},
        "jug": {},
        "pot": {},
        "frying pan": {},
        "napkin": {},
        "breakfast cereal": {
            "hypernym": "food"
        },
        "porridge": {
            "hypernym": "food"
        },
        "hunger": {
            "involves": "food"
        },
        "hungry": {},
        "i am hungry": {
            "involves": "food"
        },
        "thirsty": {
            "involves": "drink"
        },
        "i am thirsty": {
            "involves": "drink"
        },
        "come eat": {
            "involves": "food"
        },
        "the food is ready": {
            "involves": "food"
        }
    },
    "labels": {
        "en": [
            {
                "concept": "food",
                "label": {
                    "singular": "food",
                    "plural": "foods"
                }
            },
            {
                "concept": "mealtime",
                "label": "mealtime",
                "roots": [
                    "meal",
                    "time"
                ]
            },
            {
                "concept": "drink",
                "label": {
                    "singular": "drink",
                    "plural": "drinks"
                }
            },
            {
                "concept": "food and drink",
                "label": "food and drink",
                "roots": [
                    "food",
                    "drink"
                ]
            },
            {
                "concept": "vegetable",
                "label": {
                    "singular": "vegetable",
                    "plural": "vegetables"
                }
            },
            {
                "concept": "meal",
                "label": {
                    "singular": "meal",
                    "plural": "meals"
                }
            },
            {
                "concept": "breakfast",
                "label": "breakfast"
            },
            {
                "concept": "snack",
                "label": "snack"
            },
            {
                "concept": "dinner",
                "label": "dinner"
            },
            {
                "concept": "evening snack",
                "label": "evening snack",
                "meaning-only": true
            },
            {
                "concept": "appetiser",
                "label": "appetiser"
            },
            {
                "concept": "appetiser",
                "label": "starter"
            },
            {
                "concept": "main dish",
                "label": "main dish"
            },
            {
                "concept": "main dish",
                "label": "main course"
            },
            {
                "concept": "dessert",
                "label": "dessert"
            },
            {
                "concept": "macaroni casserole",
                "label": "macaroni casserole"
            },
            {
                "concept": "rice",
                "label": "rice"
            },
            {
                "concept": "pasta",
                "label": "pasta"
            },
            {
                "concept": "hamburger",
                "label": "hamburger"
            },
            {
                "concept": "wiener",
                "label": "wiener"
            },
            {
                "concept": "wiener",
                "label": "frankfurter"
            },
            {
                "concept": "wiener",
                "label": "hot dog",
                "roots": [
                    "hot",
                    "dog"
                ]
            },
            {
                "concept": "shrimp",
                "label": "shrimp"
            },
            {
                "concept": "chicken",
                "label": {
                    "singular": "chicken",
                    "plural": "chickens"
                }
            },
            {
                "concept": "beef",
                "label": "beef"
            },
            {
                "concept": "pork",
                "label": "pork"
            },
            {
                "concept": "dressing",
                "label": {
                    "singular": "dressing",
                    "plural": "dressings"
                }
            },
            {
                "concept": "ketchup",
                "label": {
                    "singular": "ketchup",
                    "plural": "ketchups"
                }
            },
            {
                "concept": "bread",
                "label": {
                    "singular": "bread",
                    "plural": "breads"
                }
            },
            {
                "concept": "karelian pasty",
                "label": "Karelian pasty"
            },
            {
                "concept": "bread roll",
                "label": [
                    "bread roll",
                    "roll"
                ],
                "roots": "bread"
            },
            {
                "concept": "butter",
                "label": "butter"
            },
            {
                "concept": "meat",
                "label": {
                    "singular": "meat",
                    "plural": "meats"
                }
            },
            {
                "concept": "milk",
                "label": {
                    "singular": "milk",
                    "plural": "milks"
                }
            },
            {
                "concept": "buttermilk",
                "label": "buttermilk",
                "roots": [
                    "butter",
                    "milk"
                ]
            },
            {
                "concept": "oat milk",
                "label": "oat milk",
                "roots": "milk"
            },
            {
                "concept": "hot chocolate",
                "label": "hot chocolate",
                "roots": [
                    "hot",
                    "chocolate"
                ]
            },
            {
                "concept": "yoghurt",
                "label": "yoghurt"
            },
            {
                "concept": "honey",
                "label": "honey"
            },
            {
                "concept": "jam",
                "label": "jam"
            },
            {
                "concept": "sausage",
                "label": {
                    "singular": "sausage",
                    "plural": "sausages"
                }
            },
            {
                "concept": "ham",
                "label": "ham"
            },
            {
                "concept": "mämmi",
                "label": {
                    "singular": "traditional Finnish Easter dessert",
                    "plural": "traditional Finnish Easter desserts"
                },
                "meaning-only": true
            },
            {
                "concept": "pizza",
                "label": {
                    "singular": "pizza",
                    "plural": "pizzas"
                }
            },
            {
                "concept": "berry",
                "label": {
                    "singular": "berry",
                    "plural": "berries"
                }
            },
            {
                "concept": "strawberry",
                "label": {
                    "singular": "strawberry",
                    "plural": "strawberries"
                },
                "roots": "berry"
            },
            {
                "concept": "cloudberry",
                "label": "cloudberry",
                "roots": "berry"
            },
            {
                "concept": "raspberry",
                "label": "raspberry",
                "roots": "berry"
            },
            {
                "concept": "bilberry",
                "label": "bilberry",
                "roots": "berry"
            },
            {
                "concept": "lingonberry",
                "label": "lingonberry",
                "roots": "berry"
            },
            {
                "concept": "lingonberry",
                "label": "cowberry",
                "roots": [
                    "cow",
                    "berry"
                ]
            },
            {
                "concept": "spice",
                "label": {
                    "singular": "spice",
                    "plural": "spices"
                }
            },
            {
                "concept": "juice",
                "label": {
                    "singular": "juice",
                    "plural": "juices"
                }
            },
            {
                "concept": "apple",
                "label": {
                    "singular": "apple",
                    "plural": "apples"
                }
            },
            {
                "concept": "potato",
                "label": {
                    "singular": "potato",
                    "plural": "potatoes"
                }
            },
            {
                "concept": "steak",
                "label": {
                    "singular": "steak",
                    "plural": "steaks"
                }
            },
            {
                "concept": "pepper",
                "label": {
                    "singular": "pepper",
                    "plural": "peppers"
                }
            },
            {
                "concept": "salad",
                "label": {
                    "singular": "salad",
                    "plural": "salads"
                }
            },
            {
                "concept": "cabbage",
                "label": {
                    "singular": "cabbage",
                    "plural": "cabbages"
                }
            },
            {
                "concept": "mustard",
                "label": {
                    "singular": "mustard",
                    "plural": "mustards"
                }
            },
            {
                "concept": "lemon",
                "label": {
                    "singular": "lemon",
                    "plural": "lemons"
                }
            },
            {
                "concept": "plum",
                "label": {
                    "singular": "plum",
                    "plural": "plums"
                }
            },
            {
                "concept": "peach",
                "label": {
                    "singular": "peach",
                    "plural": "peaches"
                }
            },
            {
                "concept": "grape",
                "label": {
                    "singular": "grape",
                    "plural": "grapes"
                }
            },
            {
                "concept": "sugar",
                "label": {
                    "singular": "sugar",
                    "plural": "sugars"
                }
            },
            {
                "concept": "salt",
                "label": {
                    "singular": "salt",
                    "plural": "salts"
                }
            },
            {
                "concept": "cucumber",
                "label": "cucumber"
            },
            {
                "concept": "carrot",
                "label": "carrot"
            },
            {
                "concept": "olive",
                "label": "olive"
            },
            {
                "concept": "soy",
                "label": "soy"
            },
            {
                "concept": "soy",
                "label": "soya"
            },
            {
                "concept": "oil",
                "label": "oil"
            },
            {
                "concept": "vinegar",
                "label": "vinegar"
            },
            {
                "concept": "tomato",
                "label": {
                    "singular": "tomato",
                    "plural": "tomatoes"
                }
            },
            {
                "concept": "sandwich",
                "label": {
                    "singular": "sandwich",
                    "plural": "sandwiches"
                }
            },
            {
                "concept": "nut",
                "label": {
                    "singular": "nut",
                    "plural": "nuts"
                }
            },
            {
                "concept": "cherry",
                "label": {
                    "singular": "cherry",
                    "plural": "cherries"
                }
            },
            {
                "concept": "currant",
                "label": "currant"
            },
            {
                "concept": "cider",
                "label": "cider"
            },
            {
                "concept": "wine",
                "label": "wine"
            },
            {
                "concept": "beer",
                "label": "beer"
            },
            {
                "concept": "soft drink",
                "label": [
                    "soft drink",
                    "softdrink"
                ],
                "roots": [
                    "soft",
                    "drink"
                ]
            },
            {
                "concept": "tea",
                "label": "tea"
            },
            {
                "concept": "pear",
                "label": {
                    "singular": "pear",
                    "plural": "pears"
                }
            },
            {
                "concept": "cauliflower",
                "label": "cauliflower",
                "roots": "flower"
            },
            {
                "concept": "egg",
                "label": "egg"
            },
            {
                "concept": "aubergine",
                "label": "aubergine"
            },
            {
                "concept": "aubergine",
                "label": "eggplant",
                "roots": [
                    "egg",
                    "plant"
                ]
            },
            {
                "concept": "corn",
                "label": "corn"
            },
            {
                "concept": "garlic",
                "label": {
                    "singular": "garlic",
                    "plural": "garlics"
                }
            },
            {
                "concept": "paprika",
                "label": "paprika"
            },
            {
                "concept": "pea",
                "label": "pea"
            },
            {
                "concept": "bean",
                "label": {
                    "singular": "bean",
                    "plural": "beans"
                }
            },
            {
                "concept": "zucchini",
                "label": "zucchini"
            },
            {
                "concept": "cookie",
                "label": {
                    "singular": "cookie",
                    "plural": "cookies"
                }
            },
            {
                "concept": "pie",
                "label": "pie"
            },
            {
                "concept": "cinnamon roll",
                "label": "cinnamon roll"
            },
            {
                "concept": "cream",
                "label": "cream"
            },
            {
                "concept": "whipped cream",
                "label": "whipped cream",
                "roots": "cream"
            },
            {
                "concept": "candy",
                "label": "candy"
            },
            {
                "concept": "chocolate",
                "label": "chocolate"
            },
            {
                "concept": "chocolate ice cream",
                "label": "chocolate ice cream",
                "roots": [
                    "chocolate",
                    "ice cream"
                ]
            },
            {
                "concept": "vanilla",
                "label": "vanilla"
            },
            {
                "concept": "banana",
                "label": {
                    "singular": "banana",
                    "plural": "bananas"
                }
            },
            {
                "concept": "pineapple",
                "label": {
                    "singular": "pineapple",
                    "plural": "pineapples"
                },
                "roots": "apple"
            },
            {
                "concept": "melon",
                "label": {
                    "singular": "melon",
                    "plural": "melons"
                }
            },
            {
                "concept": "cocktail",
                "label": {
                    "singular": "cocktail",
                    "plural": "cocktails"
                }
            },
            {
                "concept": "tray",
                "label": "tray"
            },
            {
                "concept": "fork",
                "label": {
                    "singular": "fork",
                    "plural": "forks"
                }
            },
            {
                "concept": "knife",
                "label": {
                    "singular": "knife",
                    "plural": "knives"
                }
            },
            {
                "concept": "spoon",
                "label": "spoon"
            },
            {
                "concept": "glass",
                "label": {
                    "singular": "glass",
                    "plural": "glasses"
                }
            },
            {
                "concept": "mug",
                "label": "mug"
            },
            {
                "concept": "bowl",
                "label": "bowl"
            },
            {
                "concept": "bottle",
                "label": "bottle"
            },
            {
                "concept": "plate",
                "label": {
                    "singular": "plate",
                    "plural": "plates"
                }
            },
            {
                "concept": "jug",
                "label": "jug"
            },
            {
                "concept": "pot",
                "label": "pot"
            },
            {
                "concept": "frying pan",
                "label": "frying pan"
            },
            {
                "concept": "napkin",
                "label": "napkin"
            },
            {
                "concept": "breakfast cereal",
                "label": [
                    "breakfast cereal",
                    "cereal"
                ],
                "roots": "breakfast"
            },
            {
                "concept": "porridge",
                "label": "porridge"
            },
            {
                "concept": "hunger",
                "label": "hunger"
            },
            {
                "concept": "hungry",
                "label": "hungry"
            },
            {
                "concept": "i am hungry",
                "label": "I am hungry.",
                "roots": [
                    "I am",
                    "hungry"
                ]
            },
            {
                "concept": "thirsty",
                "label": "thirsty"
            },
            {
                "concept": "i am thirsty",
                "label": "I am thirsty.",
                "roots": [
                    "I am",
                    "thirsty"
                ]
            },
            {
                "concept": "come eat",
                "label": "Come eat!",
                "roots": "to eat"
            },
            {
                "concept": "the food is ready",
                "label": "The food is ready!",
                "roots": "food"
            }
        ],
        "fi": [
            {
                "concept": "food",
                "label": {
                    "singular": "ruoka",
                    "plural": "ruoat"
                }
            },
            {
                "concept": "mealtime",
                "label": "ruokailu",
                "roots": "ruoka"
            },
            {
                "concept": "drink",
                "label": {
                    "singular": "juoma",
                    "plural": "juomat"
                }
            },
            {
                "concept": "food and drink",
                "label": "ruoka ja juoma",
                "roots": [
                    "ruoka",
                    "juoma"
                ]
            },
            {
                "concept": "vegetable",
                "label": {
                    "singular": "vihannes",
                    "plural": "vihannekset"
                }
            },
            {
                "concept": "meal",
                "label": {
                    "singular": "ateria",
                    "plural": "ateriat"
                }
            },
            {
                "concept": "breakfast",
                "label": "aamupala",
                "roots": "aamu"
            },
            {
                "concept": "breakfast",
                "label": "aamiainen",
                "roots": "aamu"
            },
            {
                "concept": "snack",
                "label": "välipala"
            },
            {
                "concept": "dinner",
                "label": "päivällinen",
                "roots": "päivä"
            },
            {
                "concept": "dinner",
                "label": "illallinen",
                "roots": "ilta"
            },
            {
                "concept": "evening snack",
                "label": "iltapala",
                "roots": "ilta"
            },
            {
                "concept": "appetiser",
                "label": "alkuruoka",
                "roots": "ruoka"
            },
            {
                "concept": "main dish",
                "label": "pääruoka",
                "roots": [
                    "pää",
                    "ruoka"
                ]
            },
            {
                "concept": "dessert",
                "label": "jälkiruoka",
                "roots": "ruoka"
            },
            {
                "concept": "macaroni casserole",
                "label": "makaronilaatikko"
            },
            {
                "concept": "rice",
                "label": "riisi"
            },
            {
                "concept": "pasta",
                "label": "pasta"
            },
            {
                "concept": "hamburger",
                "label": "hampurilainen"
            },
            {
                "concept": "wiener",
                "label": "nakki"
            },
            {
                "concept": "shrimp",
                "label": "katkarapu"
            },
            {
                "concept": "chicken",
                "label": {
                    "singular": "kana",
                    "plural": "kanat"
                }
            },
            {
                "concept": "beef",
                "label": "naudanliha",
                "roots": "liha"
            },
            {
                "concept": "pork",
                "label": "porsaanliha",
                "roots": [
                    "porsas",
                    "liha"
                ]
            },
            {
                "concept": "dressing",
                "label": {
                    "singular": "kastike",
                    "plural": "kastikkeet"
                }
            },
            {
                "concept": "ketchup",
                "label": {
                    "singular": "ketsuppi",
                    "plural": "ketsupit"
                }
            },
            {
                "concept": "bread",
                "label": {
                    "singular": "leipä",
                    "plural": "leivät"
                }
            },
            {
                "concept": "karelian pasty",
                "label": "karjalanpiirakka",
                "roots": "piirakka"
            },
            {
                "concept": "bread roll",
                "label": "sämpylä"
            },
            {
                "concept": "butter",
                "label": "voi"
            },
            {
                "concept": "meat",
                "label": {
                    "singular": "liha",
                    "plural": "lihat"
                }
            },
            {
                "concept": "milk",
                "label": {
                    "singular": "maito",
                    "plural": "maidot"
                }
            },
            {
                "concept": "buttermilk",
                "label": "piimä"
            },
            {
                "concept": "oat milk",
                "label": "kauramaito",
                "roots": "maito"
            },
            {
                "concept": "hot chocolate",
                "label": "kaakao"
            },
            {
                "concept": "yoghurt",
                "label": "jogurtti"
            },
            {
                "concept": "honey",
                "label": "hunaja"
            },
            {
                "concept": "jam",
                "label": "hillo"
            },
            {
                "concept": "sausage",
                "label": {
                    "singular": "makkara",
                    "plural": "makkarat"
                }
            },
            {
                "concept": "ham",
                "label": "kinkku"
            },
            {
                "concept": "mämmi",
                "label": {
                    "singular": "mämmi",
                    "plural": "mämmit"
                }
            },
            {
                "concept": "pizza",
                "label": {
                    "singular": "pizza",
                    "plural": "pizzat"
                }
            },
            {
                "concept": "berry",
                "label": {
                    "singular": "marja",
                    "plural": "marjat"
                }
            },
            {
                "concept": "strawberry",
                "label": {
                    "singular": "mansikka",
                    "plural": "mansikat"
                }
            },
            {
                "concept": "cloudberry",
                "label": "lakka"
            },
            {
                "concept": "raspberry",
                "label": "vadelma"
            },
            {
                "concept": "bilberry",
                "label": "mustikka",
                "note": "musta ('black') + -ikka (diminutive suffix)"
            },
            {
                "concept": "lingonberry",
                "label": "puolukka"
            },
            {
                "concept": "spice",
                "label": {
                    "singular": "mauste",
                    "plural": "mausteet"
                }
            },
            {
                "concept": "juice",
                "label": {
                    "singular": "mehu",
                    "plural": "mehut"
                }
            },
            {
                "concept": "apple",
                "label": {
                    "singular": "omena",
                    "plural": "omenat"
                }
            },
            {
                "concept": "potato",
                "label": {
                    "singular": "peruna",
                    "plural": "perunat"
                }
            },
            {
                "concept": "steak",
                "label": {
                    "singular": "pihvi",
                    "plural": "pihvit"
                }
            },
            {
                "concept": "pepper",
                "label": {
                    "singular": "pippuri",
                    "plural": "pippurit"
                }
            },
            {
                "concept": "salad",
                "label": {
                    "singular": "salaatti",
                    "plural": "salaatit"
                }
            },
            {
                "concept": "cabbage",
                "label": {
                    "singular": "kaali",
                    "plural": "kaalit"
                }
            },
            {
                "concept": "mustard",
                "label": {
                    "singular": "sinappi",
                    "plural": "sinapit"
                }
            },
            {
                "concept": "lemon",
                "label": {
                    "singular": "sitruuna",
                    "plural": "sitruunat"
                }
            },
            {
                "concept": "plum",
                "label": {
                    "singular": "luumu",
                    "plural": "luumut"
                }
            },
            {
                "concept": "peach",
                "label": {
                    "singular": "persikka",
                    "plural": "persikat"
                }
            },
            {
                "concept": "grape",
                "label": {
                    "singular": "viinirypäle",
                    "plural": "viinirypäleet"
                },
                "roots": "viini"
            },
            {
                "concept": "sugar",
                "label": {
                    "singular": "sokeri",
                    "plural": "sokerit"
                }
            },
            {
                "concept": "salt",
                "label": {
                    "singular": "suola",
                    "plural": "suolat"
                }
            },
            {
                "concept": "carrot",
                "label": "porkkana"
            },
            {
                "concept": "olive",
                "label": "oliivi"
            },
            {
                "concept": "soy",
                "label": "soija"
            },
            {
                "concept": "oil",
                "label": "öljy"
            },
            {
                "concept": "vinegar",
                "label": "etikka"
            },
            {
                "concept": "tomato",
                "label": {
                    "singular": "tomaatti",
                    "plural": "tomaatit"
                }
            },
            {
                "concept": "sandwich",
                "label": {
                    "singular": "voileipä",
                    "plural": "voileivät"
                },
                "roots": [
                    "voi",
                    "leipä"
                ]
            },
            {
                "concept": "nut",
                "label": {
                    "singular": "pähkinä",
                    "plural": "pähkinät"
                }
            },
            {
                "concept": "cherry",
                "label": {
                    "singular": "kirsikka",
                    "plural": "kirsikat"
                }
            },
            {
                "concept": "currant",
                "label": "viinimarja",
                "roots": [
                    "viini",
                    "marja"
                ]
            },
            {
                "concept": "cider",
                "label": "siideri"
            },
            {
                "concept": "wine",
                "label": "viini"
            },
            {
                "concept": "beer",
                "label": "olut"
            },
            {
                "concept": "soft drink",
                "label": "limu"
            },
            {
                "concept": "tea",
                "label": "tee"
            },
            {
                "concept": "pear",
                "label": {
                    "singular": "päärynä",
                    "plural": "päärynät"
                }
            },
            {
                "concept": "cauliflower",
                "label": "kukkakaali",
                "roots": [
                    "kukka",
                    "kaali"
                ]
            },
            {
                "concept": "egg",
                "label": "muna"
            },
            {
                "concept": "aubergine",
                "label": "munakoiso",
                "roots": "muna"
            },
            {
                "concept": "corn",
                "label": "maissi"
            },
            {
                "concept": "garlic",
                "label": {
                    "singular": "valkosipuli",
                    "plural": "valkosipulit"
                },
                "note": "valko- ('white') + sipuli ('onion')",
                "roots": [
                    "valkoinen",
                    "sipuli"
                ]
            },
            {
                "concept": "paprika",
                "label": "paprika"
            },
            {
                "concept": "pea",
                "label": "herne"
            },
            {
                "concept": "bean",
                "label": {
                    "singular": "papu",
                    "plural": "pavut"
                }
            },
            {
                "concept": "zucchini",
                "label": "kesäkurpitsa",
                "roots": "kesä"
            },
            {
                "concept": "cookie",
                "label": {
                    "singular": "keksi",
                    "plural": "keksit"
                }
            },
            {
                "concept": "pie",
                "label": "piirakka"
            },
            {
                "concept": "cinnamon roll",
                "label": "korvapuusti",
                "roots": "korva"
            },
            {
                "concept": "cream",
                "label": "kerma"
            },
            {
                "concept": "whipped cream",
                "label": "kermavaahto",
                "roots": "kerma"
            },
            {
                "concept": "candy",
                "label": "karkki"
            },
            {
                "concept": "chocolate",
                "label": "suklaa"
            },
            {
                "concept": "chocolate ice cream",
                "label": "suklaajäätelö",
                "roots": [
                    "suklaa",
                    "jäätelö"
                ]
            },
            {
                "concept": "vanilla",
                "label": "vanilja"
            },
            {
                "concept": "banana",
                "label": {
                    "singular": "banaani",
                    "plural": "banaanit"
                }
            },
            {
                "concept": "pineapple",
                "label": {
                    "singular": "ananas",
                    "plural": "ananakset"
                }
            },
            {
                "concept": "melon",
                "label": {
                    "singular": "meloni",
                    "plural": "melonit"
                }
            },
            {
                "concept": "cocktail",
                "label": {
                    "singular": "cocktail",
                    "plural": "cocktailit"
                }
            },
            {
                "concept": "tray",
                "label": "tarjotin"
            },
            {
                "concept": "fork",
                "label": {
                    "singular": "haarukka",
                    "plural": "haarukat"
                }
            },
            {
                "concept": "knife",
                "label": {
                    "singular": "veitsi",
                    "plural": "veitset"
                }
            },
            {
                "concept": "spoon",
                "label": "lusikka"
            },
            {
                "concept": "glass",
                "label": {
                    "singular": "lasi",
                    "plural": "lasit"
                }
            },
            {
                "concept": "mug",
                "label": "muki"
            },
            {
                "concept": "bowl",
                "label": "kulho"
            },
            {
                "concept": "bottle",
                "label": "pullo"
            },
            {
                "concept": "plate",
                "label": {
                    "singular": "lautanen",
                    "plural": "lautaset"
                }
            },
            {
                "concept": "jug",
                "label": "kannu"
            },
            {
                "concept": "pot",
                "label": "kattila"
            },
            {
                "concept": "frying pan",
                "label": "paistinpannu"
            },
            {
                "concept": "napkin",
                "label": "lautasliina"
            },
            {
                "concept": "breakfast cereal",
                "label": "murot"
            },
            {
                "concept": "porridge",
                "label": "puuro"
            },
            {
                "concept": "hunger",
                "label": "nälkä"
            },
            {
                "concept": "hungry",
                "label": "nälkäinen"
            },
            {
                "concept": "i am hungry",
                "label": "Minulla on nälkä.",
                "roots": [
                    "minulla on",
                    "nälkä"
                ]
            },
            {
                "concept": "thirsty",
                "label": "jano"
            },
            {
                "concept": "i am thirsty",
                "label": "Minulla on jano.",
                "roots": [
                    "minulla on",
                    "jano"
                ]
            },
            {
                "concept": "come eat",
                "label": "Tulkaa syömään!"
            },
            {
                "concept": "the food is ready",
                "label": "Ruoka on valmista!",
                "roots": "ruoka"
            }
        ],
        "nl": [
            {
                "concept": "food",
                "label": "het voedsel"
            },
            {
                "concept": "food",
                "label": "het eten"
            },
            {
                "concept": "mealtime",
                "label": "het eten",
                "tip": "activity"
            },
            {
                "concept": "drink",
                "label": {
                    "singular": "de drank",
                    "plural": "de dranken"
                }
            },
            {
                "concept": "food and drink",
                "label": "het eten en drinken",
                "roots": "het eten"
            },
            {
                "concept": "vegetable",
                "label": {
                    "singular": "de groente",
                    "plural": [
                        "de groenten",
                        "de groentes"
                    ]
                }
            },
            {
                "concept": "meal",
                "label": {
                    "singular": "de maaltijd",
                    "plural": "de maaltijden"
                },
                "roots": "de tijd"
            },
            {
                "concept": "breakfast",
                "label": "het ontbijt"
            },
            {
                "concept": "snack",
                "label": "het tussendoortje",
                "roots": "tussen"
            },
            {
                "concept": "dinner",
                "label": "het avondeten",
                "roots": [
                    "de avond",
                    "het eten"
                ]
            },
            {
                "concept": "evening snack",
                "label": "tussendoortje in de avond",
                "meaning-only": true
            },
            {
                "concept": "appetiser",
                "label": "het voorgerecht"
            },
            {
                "concept": "main dish",
                "label": "het hoofdgerecht"
            },
            {
                "concept": "dessert",
                "label": "het dessert"
            },
            {
                "concept": "dessert",
                "label": "het toetje"
            },
            {
                "concept": "dessert",
                "label": "het nagerecht"
            },
            {
                "concept": "macaroni casserole",
                "label": "de macaronischotel"
            },
            {
                "concept": "rice",
                "label": "de rijst"
            },
            {
                "concept": "pasta",
                "label": "de pasta"
            },
            {
                "concept": "hamburger",
                "label": "de hamburger"
            },
            {
                "concept": "wiener",
                "label": "de knakworst",
                "roots": "de worst"
            },
            {
                "concept": "shrimp",
                "label": "de garnaal"
            },
            {
                "concept": "chicken",
                "label": {
                    "singular": "de kip",
                    "plural": "de kippen"
                }
            },
            {
                "concept": "beef",
                "label": "het rundvlees",
                "roots": "het vlees"
            },
            {
                "concept": "pork",
                "label": "het varkensvlees",
                "roots": "het vlees"
            },
            {
                "concept": "dressing",
                "label": {
                    "singular": "de dressing",
                    "plural": "de dressings"
                }
            },
            {
                "concept": "ketchup",
                "label": "de ketchup"
            },
            {
                "concept": "bread",
                "label": {
                    "singular": "het brood",
                    "plural": "de broden"
                }
            },
            {
                "concept": "karelian pasty",
                "label": "Karelisch pasteitje"
            },
            {
                "concept": "bread roll",
                "label": "het broodje",
                "roots": "het brood"
            },
            {
                "concept": "butter",
                "label": "de boter"
            },
            {
                "concept": "meat",
                "label": {
                    "singular": "het vlees",
                    "plural": "de vlezen"
                }
            },
            {
                "concept": "milk",
                "label": "de melk"
            },
            {
                "concept": "buttermilk",
                "label": "de karnemelk",
                "roots": "de melk"
            },
            {
                "concept": "oat milk",
                "label": "de havermelk",
                "roots": "de melk"
            },
            {
                "concept": "hot chocolate",
                "label": "de chocolademelk",
                "roots": [
                    "de chocolade",
                    "de melk"
                ]
            },
            {
                "concept": "yoghurt",
                "label": "de yoghurt"
            },
            {
                "concept": "honey",
                "label": "de honing"
            },
            {
                "concept": "jam",
                "label": "de jam"
            },
            {
                "concept": "sausage",
                "label": {
                    "singular": "de worst",
                    "plural": "de worsten"
                }
            },
            {
                "concept": "ham",
                "label": "de ham"
            },
            {
                "concept": "mämmi",
                "label": {
                    "singular": "traditioneel Fins paasdessert",
                    "plural": "traditionele Finse paasdesserts"
                },
                "meaning-only": true
            },
            {
                "concept": "pizza",
                "label": {
                    "singular": "de pizza",
                    "plural": "de pizza's"
                }
            },
            {
                "concept": "berry",
                "label": {
                    "singular": "de bes",
                    "plural": "de bessen"
                }
            },
            {
                "concept": "strawberry",
                "label": {
                    "singular": "de aardbei",
                    "plural": "de aardbeien"
                }
            },
            {
                "concept": "cloudberry",
                "label": "de moerasbraam"
            },
            {
                "concept": "raspberry",
                "label": "de framboos"
            },
            {
                "concept": "bilberry",
                "label": "de bosbes",
                "roots": [
                    "het bos",
                    "de bes"
                ]
            },
            {
                "concept": "lingonberry",
                "label": "de vossenbes",
                "roots": [
                    "de vos",
                    "de bes"
                ]
            },
            {
                "concept": "spice",
                "label": {
                    "singular": "het kruid",
                    "plural": "de kruiden"
                }
            },
            {
                "concept": "juice",
                "label": {
                    "singular": "het sap",
                    "plural": "de sappen"
                }
            },
            {
                "concept": "apple",
                "label": {
                    "singular": "de appel",
                    "plural": "de appels"
                }
            },
            {
                "concept": "potato",
                "label": {
                    "singular": "de aardappel",
                    "plural": "de aardappels"
                },
                "roots": [
                    "de aarde",
                    "de appel"
                ]
            },
            {
                "concept": "steak",
                "label": {
                    "singular": "de biefstuk",
                    "plural": "de biefstukken"
                }
            },
            {
                "concept": "steak",
                "label": {
                    "singular": "de steak",
                    "plural": "de steaks"
                }
            },
            {
                "concept": "pepper",
                "label": {
                    "singular": "de peper",
                    "plural": "de pepers"
                }
            },
            {
                "concept": "salad",
                "label": {
                    "singular": "de salade",
                    "plural": "de salades"
                }
            },
            {
                "concept": "cabbage",
                "label": {
                    "singular": "de kool",
                    "plural": "de kolen"
                }
            },
            {
                "concept": "mustard",
                "label": {
                    "singular": "de mosterd",
                    "plural": "de mosterds"
                }
            },
            {
                "concept": "lemon",
                "label": {
                    "singular": "de citroen",
                    "plural": "de citroenen"
                }
            },
            {
                "concept": "plum",
                "label": {
                    "singular": "de pruim",
                    "plural": "de pruimen"
                }
            },
            {
                "concept": "peach",
                "label": {
                    "singular": "de perzik",
                    "plural": "de perziken"
                }
            },
            {
                "concept": "grape",
                "label": {
                    "singular": "de druif",
                    "plural": "de druiven"
                }
            },
            {
                "concept": "sugar",
                "label": {
                    "singular": "de suiker",
                    "plural": "de suikers"
                }
            },
            {
                "concept": "salt",
                "label": {
                    "singular": "het zout",
                    "plural": "de zouten"
                }
            },
            {
                "concept": "cucumber",
                "label": "de komkommer"
            },
            {
                "concept": "carrot",
                "label": "de wortel"
            },
            {
                "concept": "olive",
                "label": "de olijf"
            },
            {
                "concept": "soy",
                "label": "de soja"
            },
            {
                "concept": "oil",
                "label": "de olie"
            },
            {
                "concept": "vinegar",
                "label": "de azijn"
            },
            {
                "concept": "tomato",
                "label": {
                    "singular": "de tomaat",
                    "plural": "de tomaten"
                }
            },
            {
                "concept": "sandwich",
                "label": {
                    "singular": "de boterham",
                    "plural": "de boterhammen"
                },
                "roots": [
                    "de boter",
                    "de ham"
                ]
            },
            {
                "concept": "nut",
                "label": {
                    "singular": "de noot",
                    "plural": "de noten"
                }
            },
            {
                "concept": "cherry",
                "label": {
                    "singular": "de kers",
                    "plural": "de kersen"
                }
            },
            {
                "concept": "currant",
                "label": "de aalbes",
                "roots": "de bes"
            },
            {
                "concept": "cider",
                "label": "de cider"
            },
            {
                "concept": "wine",
                "label": "de wijn"
            },
            {
                "concept": "beer",
                "label": "het bier"
            },
            {
                "concept": "soft drink",
                "label": "de frisdrank",
                "roots": "de drank"
            },
            {
                "concept": "tea",
                "label": "de thee"
            },
            {
                "concept": "pear",
                "label": {
                    "singular": "de peer",
                    "plural": "de peren"
                }
            },
            {
                "concept": "cauliflower",
                "label": "de bloemkool",
                "roots": [
                    "de bloem",
                    "de kool"
                ]
            },
            {
                "concept": "egg",
                "label": "het ei"
            },
            {
                "concept": "aubergine",
                "label": "de aubergine"
            },
            {
                "concept": "corn",
                "label": "de maïs"
            },
            {
                "concept": "garlic",
                "label": {
                    "singular": "de knoflook",
                    "plural": "de knofloken"
                }
            },
            {
                "concept": "paprika",
                "label": "de paprika"
            },
            {
                "concept": "pea",
                "label": "de erwt"
            },
            {
                "concept": "bean",
                "label": {
                    "singular": "de boon",
                    "plural": "de bonen"
                }
            },
            {
                "concept": "zucchini",
                "label": "de courgette"
            },
            {
                "concept": "cookie",
                "label": {
                    "singular": "het koekje",
                    "plural": "de koekjes"
                }
            },
            {
                "concept": "pie",
                "label": "de vlaai"
            },
            {
                "concept": "cinnamon roll",
                "label": "het kaneelbroodje",
                "roots": "het brood"
            },
            {
                "concept": "cream",
                "label": "de room"
            },
            {
                "concept": "whipped cream",
                "label": "de slagroom",
                "roots": "de room"
            },
            {
                "concept": "candy",
                "label": "het snoepje"
            },
            {
                "concept": "chocolate",
                "label": "de chocolade"
            },
            {
                "concept": "chocolate ice cream",
                "label": [
                    "het chocolade-ijsje",
                    "het chocolade-ijs"
                ],
                "roots": [
                    "de chocolade",
                    "het ijs"
                ]
            },
            {
                "concept": "vanilla",
                "label": "vanille"
            },
            {
                "concept": "banana",
                "label": {
                    "singular": "de banaan",
                    "plural": "de bananen"
                }
            },
            {
                "concept": "pineapple",
                "label": {
                    "singular": "de ananas",
                    "plural": "de ananassen"
                }
            },
            {
                "concept": "melon",
                "label": {
                    "singular": "de meloen",
                    "plural": "de meloenen"
                }
            },
            {
                "concept": "cocktail",
                "label": {
                    "singular": "de cocktail",
                    "plural": "de cocktails"
                }
            },
            {
                "concept": "tray",
                "label": "het dienblad"
            },
            {
                "concept": "fork",
                "label": {
                    "singular": "de vork",
                    "plural": "de vorken"
                }
            },
            {
                "concept": "knife",
                "label": {
                    "singular": "het mes",
                    "plural": "de messen"
                }
            },
            {
                "concept": "spoon",
                "label": "de lepel"
            },
            {
                "concept": "glass",
                "label": {
                    "singular": "het glas",
                    "plural": "de glazen"
                }
            },
            {
                "concept": "mug",
                "label": "de mok"
            },
            {
                "concept": "bowl",
                "label": "de kom"
            },
            {
                "concept": "bottle",
                "label": "de fles"
            },
            {
                "concept": "plate",
                "label": {
                    "singular": "het bord",
                    "plural": "de borden"
                }
            },
            {
                "concept": "jug",
                "label": "de kan"
            },
            {
                "concept": "pot",
                "label": "de pan"
            },
            {
                "concept": "frying pan",
                "label": "de koekenpan",
                "roots": "de pan"
            },
            {
                "concept": "frying pan",
                "label": "de braadpan",
                "roots": "de pan"
            },
            {
                "concept": "napkin",
                "label": "het servet"
            },
            {
                "concept": "breakfast cereal",
                "label": "de ontbijtgranen",
                "roots": "het ontbijt"
            },
            {
                "concept": "porridge",
                "label": "de pap"
            },
            {
                "concept": "hunger",
                "label": "de honger"
            },
            {
                "concept": "hungry",
                "label": "hongerig",
                "roots": "de honger"
            },
            {
                "concept": "i am hungry",
                "label": "Ik heb honger.",
                "roots": [
                    "ik heb",
                    "de honger"
                ]
            },
            {
                "concept": "thirsty",
                "label": "de dorst"
            },
            {
                "concept": "i am thirsty",
                "label": "Ik heb dorst.",
                "roots": [
                    "ik heb",
                    "de dorst"
                ]
            },
            {
                "concept": "come eat",
                "label": "Kom eten!"
            },
            {
                "concept": "the food is ready",
                "label": "Het eten is klaar!",
                "roots": "het eten"
            }
        ]
    }
}
