{
    "concepts": {
        "to the left": {
            "antonym": "to the right",
            "example": "alice sits to the left of bob"
        },
        "alice sits to the left of bob": {
            "antonym": "alice sits to the right of bob"
        }
    },
    "labels": {
        "en": [
            {
                "concept": "to the left",
                "label": "to the left"
            },
            {
                "concept": "alice sits to the left of bob",
                "label": "Alice sits to the left of Bob.",
                "roots": [
                    "she sits",
                    "to the left"
                ]
            }
        ],
        "fi": [
            {
                "concept": "to the left",
                "label": "vasemmalla puolella"
            },
            {
                "concept": "alice sits to the left of bob",
                "label": "Alice istuu Bobin vasemmalla puolella.",
                "roots": [
                    "hän istuu",
                    "vasemmalla puolella"
                ]
            }
        ],
        "nl": [
            {
                "concept": "to the left",
                "label": "aan de linkerkant"
            },
            {
                "concept": "alice sits to the left of bob",
                "label": "Alice zit aan de linkerkant van Bob.",
                "roots": [
                    "zij zit",
                    "aan de linkerkant"
                ]
            }
        ]
    }
}
