{
    "concepts": {
        "allergy": {
            "involves": "health"
        }
    },
    "labels": {
        "en": [
            {
                "concept": "allergy",
                "label": "allergy"
            }
        ],
        "fi": [
            {
                "concept": "allergy",
                "label": "allergia"
            }
        ],
        "nl": [
            {
                "concept": "allergy",
                "label": "de allergie"
            }
        ]
    }
}
