{
    "concepts": {
        "enjoy your meal": {}
    },
    "labels": {
        "en": [
            {
                "concept": "enjoy your meal",
                "label": "Enjoy your meal!",
                "roots": "meal"
            }
        ],
        "fi": [
            {
                "concept": "enjoy your meal",
                "label": "Hyvää ruokahalua!",
                "roots": [
                    "hyvä",
                    "ruoka"
                ]
            }
        ],
        "nl": [
            {
                "concept": "enjoy your meal",
                "label": "Eet smakelijk!",
                "roots": "eten"
            }
        ]
    }
}
