{
    "concepts": {
        "star": {
            "holonym": "galaxy"
        }
    },
    "labels": {
        "en": [
            {
                "concept": "star",
                "label": {
                    "singular": "star",
                    "plural": "stars"
                }
            }
        ],
        "fi": [
            {
                "concept": "star",
                "label": {
                    "singular": "tähti",
                    "plural": "tähdet"
                }
            }
        ],
        "nl": [
            {
                "concept": "star",
                "label": {
                    "singular": "de ster",
                    "plural": "de sterren"
                }
            }
        ]
    }
}
