{
    "concepts": {
        "tomorrow": {
            "hypernym": "day",
            "labels": {
                "en": "tomorrow",
                "fi": "huomenna",
                "nl": "morgen"
            }
        },
        "the day after tomorrow": {
            "hypernym": "day",
            "roots": {
                "en": [
                    "day",
                    "after",
                    "tomorrow"
                ],
                "fi": [
                    "after",
                    "tomorrow"
                ],
                "nl": [
                    "after",
                    "tomorrow"
                ]
            },
            "labels": {
                "en": "the day after tomorrow",
                "fi": "ylihuomenna",
                "nl": "overmorgen"
            }
        },
        "tomorrow it is tuesday": {
            "roots": [
                "tomorrow",
                "to be",
                "tuesday"
            ],
            "labels": {
                "en": "Tomorrow it is Tuesday.",
                "fi": "Huomenna on tiistai.",
                "nl": "Morgen is het dinsdag."
            }
        },
        "tomorrow it is sunday": {
            "roots": [
                "tomorrow",
                "to be",
                "sunday"
            ],
            "labels": {
                "en": "Tomorrow it is sunday.",
                "fi": "Huomenna on sunnuntai.",
                "nl": "Morgen is het zondag."
            }
        }
    }
}
